hued/__init__.py
hued/analysis.py
hued/colors.py
hued/conversions.py
hued/palettes.py
hued-1.0.6.dist-info/licenses/LICENSE
hued-1.0.6.dist-info/METADATA
hued-1.0.6.dist-info/WHEEL
hued-1.0.6.dist-info/top_level.txt
hued-1.0.6.dist-info/RECORD
